alissonSomav3/__init__.py
alissonSomav3/somav2.py
alissonSomav3-0.1.dist-info/LICENSE
alissonSomav3-0.1.dist-info/METADATA
alissonSomav3-0.1.dist-info/WHEEL
alissonSomav3-0.1.dist-info/top_level.txt
alissonSomav3-0.1.dist-info/RECORD
